<?xml version="1.0" encoding="utf-8"?>
<LanguageData>
    <!-- EN: Turn pointer to {0} -->
	<AnomaliesExpected.Speedometer.TurnPointer>調整指針至{0}</AnomaliesExpected.Speedometer.TurnPointer>
    <!-- EN: Turn pointer to {0} [Current] -->
	<AnomaliesExpected.Speedometer.TurnPointerCurrent>調整指針至{0} [當前檔位]</AnomaliesExpected.Speedometer.TurnPointerCurrent>
    <!-- EN: Turn pointer to {0} [Disabled] -->
	<AnomaliesExpected.Speedometer.TurnPointerDisabled>調整指針至{0} [不可用]</AnomaliesExpected.Speedometer.TurnPointerDisabled>
    <!-- EN: Rotate screw -->
	<AnomaliesExpected.Speedometer.TurnPointer.Label>旋轉螺絲</AnomaliesExpected.Speedometer.TurnPointer.Label>
    <!-- EN: Rotate screw to turn pointer to a different value -->
	<AnomaliesExpected.Speedometer.TurnPointer.Desc>旋轉螺絲，將指針調至某個值</AnomaliesExpected.Speedometer.TurnPointer.Desc>
	
    <!-- EN: Take off {0}? -->
	<AnomaliesExpected.Speedometer.TakeOff>取下{0}嗎?</AnomaliesExpected.Speedometer.TakeOff>
    <!-- EN: Take off -->
	<AnomaliesExpected.Speedometer.TakeOff.Label>取下</AnomaliesExpected.Speedometer.TakeOff.Label>
    <!-- EN: Take off {0} from yourself -->
	<AnomaliesExpected.Speedometer.TakeOff.Desc>將{0}從身體中取下</AnomaliesExpected.Speedometer.TakeOff.Desc>
</LanguageData>
