<?xml version="1.0" encoding="utf-8"?>
<LanguageData>

    <!-- EN: snow army entities -->
    <AE_SnowArmy.label>冰雪军团实体</AE_SnowArmy.label>
    <!-- EN: Snow army -->
    <AE_SnowArmy.fixedName>冰雪军团</AE_SnowArmy.fixedName>
    <!-- EN: [OG] -->
    <AE_SnowArmy.leaderTitle>领袖</AE_SnowArmy.leaderTitle>
    <!-- EN: snow soldier -->
    <AE_SnowArmy.pawnSingular>冰雪士兵</AE_SnowArmy.pawnSingular>
    <!-- EN: snow army -->
    <AE_SnowArmy.pawnsPlural>冰雪军团</AE_SnowArmy.pawnsPlural>

    <!-- EN: {0} from {1} are attacking your {2}. -->
    <AE_SnowArmy.messageDefendersAttacking>来自{1}的{0}正在攻击你的{2}。</AE_SnowArmy.messageDefendersAttacking>

</LanguageData>